<?xml version="1.0" encoding="utf-8"?>
<combined-fits>
<fits xmlns="http://hul.harvard.edu/ois/xml/ns/fits/fits_output" xmlns:xsi="http://www.w3.org/2001/XMLSchema-instance" xsi:schemaLocation="http://hul.harvard.edu/ois/xml/ns/fits/fits_output http://hul.harvard.edu/ois/xml/xsd/fits/fits_output.xsd" version="1.2.0" timestamp="11/14/17 6:43 PM">
  <identification status="SINGLE_RESULT">
    <identity format="TrueType Font" mimetype="application/x-font-ttf" toolname="FITS" toolversion="1.2.0">
      <tool toolname="Tika" toolversion="1.10" />
    </identity>
  </identification>
  <fileinfo>
    <filepath toolname="OIS File Information" toolversion="0.2" status="SINGLE_RESULT">/home/digipres/Desktop/Russell_ProtoAips/protoaips_open/rbrl-157-er-000083_Backups/objects/intra-backup67.nod</filepath>
    <filename toolname="OIS File Information" toolversion="0.2" status="SINGLE_RESULT">intra-backup67.nod</filename>
    <size toolname="OIS File Information" toolversion="0.2" status="SINGLE_RESULT">2407800</size>
    <md5checksum toolname="OIS File Information" toolversion="0.2" status="SINGLE_RESULT">d730b7a30c4c17bab07369d9d2152cc2</md5checksum>
    <fslastmodified toolname="OIS File Information" toolversion="0.2" status="SINGLE_RESULT">970552114000</fslastmodified>
  </fileinfo>
  <filestatus />
  <metadata />
  <statistics fitsExecutionTime="1218">
    <tool toolname="MediaInfo" toolversion="0.7.75" status="did not run" />
    <tool toolname="OIS Audio Information" toolversion="0.1" status="did not run" />
    <tool toolname="ADL Tool" toolversion="0.1" status="did not run" />
    <tool toolname="VTT Tool" toolversion="0.1" status="did not run" />
    <tool toolname="Droid" toolversion="6.3" executionTime="116" />
    <tool toolname="Jhove" toolversion="1.16" executionTime="1214" />
    <tool toolname="file utility" toolversion="5.11" executionTime="186" />
    <tool toolname="Exiftool" toolversion="10.00" executionTime="177" />
    <tool toolname="NLNZ Metadata Extractor" toolversion="3.6GA" status="did not run" />
    <tool toolname="OIS File Information" toolversion="0.2" executionTime="257" />
    <tool toolname="OIS XML Metadata" toolversion="0.2" status="did not run" />
    <tool toolname="ffident" toolversion="0.2" executionTime="28" />
    <tool toolname="Tika" toolversion="1.10" executionTime="266" />
  </statistics>
</fits>

<fits xmlns="http://hul.harvard.edu/ois/xml/ns/fits/fits_output" xmlns:xsi="http://www.w3.org/2001/XMLSchema-instance" xsi:schemaLocation="http://hul.harvard.edu/ois/xml/ns/fits/fits_output http://hul.harvard.edu/ois/xml/xsd/fits/fits_output.xsd" version="1.2.0" timestamp="11/14/17 6:43 PM">
  <identification status="SINGLE_RESULT">
    <identity format="TrueType Font" mimetype="application/x-font-ttf" toolname="FITS" toolversion="1.2.0">
      <tool toolname="Tika" toolversion="1.10" />
    </identity>
  </identification>
  <fileinfo>
    <filepath toolname="OIS File Information" toolversion="0.2" status="SINGLE_RESULT">/home/digipres/Desktop/Russell_ProtoAips/protoaips_open/rbrl-157-er-000083_Backups/objects/intra-backup68.nod</filepath>
    <filename toolname="OIS File Information" toolversion="0.2" status="SINGLE_RESULT">intra-backup68.nod</filename>
    <size toolname="OIS File Information" toolversion="0.2" status="SINGLE_RESULT">2407800</size>
    <md5checksum toolname="OIS File Information" toolversion="0.2" status="SINGLE_RESULT">24a91d36e620260f433e661e0dadccf7</md5checksum>
    <fslastmodified toolname="OIS File Information" toolversion="0.2" status="SINGLE_RESULT">970661604000</fslastmodified>
  </fileinfo>
  <filestatus />
  <metadata />
  <statistics fitsExecutionTime="1618">
    <tool toolname="MediaInfo" toolversion="0.7.75" status="did not run" />
    <tool toolname="OIS Audio Information" toolversion="0.1" status="did not run" />
    <tool toolname="ADL Tool" toolversion="0.1" status="did not run" />
    <tool toolname="VTT Tool" toolversion="0.1" status="did not run" />
    <tool toolname="Droid" toolversion="6.3" executionTime="154" />
    <tool toolname="Jhove" toolversion="1.16" executionTime="1607" />
    <tool toolname="file utility" toolversion="5.11" executionTime="503" />
    <tool toolname="Exiftool" toolversion="10.00" executionTime="494" />
    <tool toolname="NLNZ Metadata Extractor" toolversion="3.6GA" status="did not run" />
    <tool toolname="OIS File Information" toolversion="0.2" executionTime="416" />
    <tool toolname="OIS XML Metadata" toolversion="0.2" status="did not run" />
    <tool toolname="ffident" toolversion="0.2" executionTime="430" />
    <tool toolname="Tika" toolversion="1.10" executionTime="504" />
  </statistics>
</fits>

</combined-fits>
